{
  "project_info": {
    "project_number": "474960089431",
    "project_id": "canadapp",
    "storage_bucket": "canadapp.firebasestorage.app"
  },
  "client": [
    {
      "client_info": {
        "mobilesdk_app_id": "1:474960089431:android:5af04688e27b6f5b4e2e12",
        "android_client_info": {
          "package_name": "com.example.canadapp"
        }
      },
      "oauth_client": [],
      "api_key": [
        {
          "current_key": "AIzaSyBIiN8xrbIjbRLNsUk7x3v1MLAcVbSzW84"
        }
      ],
      "services": {
        "appinvite_service": {
          "other_platform_oauth_client": []
        }
      }
    }
  ],
  "configuration_version": "1"
}